rio_rgbify/__init__.py
rio_rgbify/encoders.py
rio_rgbify/mbtiler.py
rio_rgbify/scripts/__init__.py
rio_rgbify/scripts/cli.py
rio_rgbify-0.4.0.dist-info/LICENSE
rio_rgbify-0.4.0.dist-info/METADATA
rio_rgbify-0.4.0.dist-info/WHEEL
rio_rgbify-0.4.0.dist-info/entry_points.txt
rio_rgbify-0.4.0.dist-info/top_level.txt
rio_rgbify-0.4.0.dist-info/RECORD
