Metadata-Version: 2.1
Name: rio-rgbify
Version: 0.4.0
Summary: Encode arbitrary bit depth rasters in psuedo base-256 as RGB
Home-page: https://github.com/mapbox/rio-rgbify
Author: Damon Burgett
Author-email: damon@mapbox.com
License: BSD
Platform: UNKNOWN
Requires-Dist: click
Requires-Dist: rasterio (~=1.0)
Requires-Dist: rio-mucho
Requires-Dist: Pillow
Requires-Dist: mercantile
Provides-Extra: dev
Requires-Dist: pytest ; extra == 'dev'
Requires-Dist: pytest-cov ; extra == 'dev'
Requires-Dist: codecov ; extra == 'dev'
Requires-Dist: hypothesis ; extra == 'dev'
Requires-Dist: raster-tester ; extra == 'dev'
Requires-Dist: pre-commit ; extra == 'dev'
Provides-Extra: test
Requires-Dist: pytest ; extra == 'test'
Requires-Dist: pytest-cov ; extra == 'test'
Requires-Dist: codecov ; extra == 'test'
Requires-Dist: hypothesis ; extra == 'test'
Requires-Dist: raster-tester ; extra == 'test'
